fmp_api_python/__init__.py
fmp_api_python/constants.py
fmp_api_python/fmp.py
fmp_api_python-1.1.0.dist-info/LICENSE
fmp_api_python-1.1.0.dist-info/METADATA
fmp_api_python-1.1.0.dist-info/WHEEL
fmp_api_python-1.1.0.dist-info/top_level.txt
fmp_api_python-1.1.0.dist-info/RECORD
