Metadata-Version: 2.1
Name: fmp-api-python
Version: 1.1.0
Summary: Financial Modeling Prep API Wrapper
Author-email: Nicholas Kelly <nicholas.victor.kelly@gmail.com>
License: MIT License        
Project-URL: Homepage, https://github.com/NicholasKelly15/fmp-api-python
Keywords: fmp,api,wrapper,finance,stocks
Classifier: License :: OSI Approved :: MIT License
Classifier: Programming Language :: Python
Classifier: Programming Language :: Python :: 3
License-File: LICENSE
Requires-Dist: pandas
